<root>
<software>
<name name="B0 and eddy current correction for DTI" nitrc="https://www.nitrc.org/projects/dtic" />
<description> Software tool (excecutable and source code in C and C++) to correct distortions in diffusion MR images that are generated by main magnetic field inhomogeneities and eddy current induced fields generated from the direction-dependent diffusion encoding </description>
<license>GNU General Public License (GPL)</license>
<category>Other Software Resource</category>
<platform>Microsoft</platform>
<input>ANALYZE</input>
<output>ANALYZE</output>
<release>Apr 23, 2008</release>
<homepage>http://nbirn.net/tools/bo_eddy/index.shtm</homepage>
<HBP>External</HBP>
<deployment>Standalone</deployment>
<display>Desktop</display>
</software>
</root>